{
    "PlayerAgent": {
        "checkpoints": [
            {
                "steps": 112686,
                "file_path": "results/Multiple_CubeTarget_11/PlayerAgent/PlayerAgent-112686.onnx",
                "reward": 6.36833330988884,
                "creation_time": 1725736886.711395,
                "auxillary_file_paths": [
                    "results/Multiple_CubeTarget_11/PlayerAgent/PlayerAgent-112686.pt"
                ]
            }
        ],
        "final_checkpoint": {
            "steps": 112686,
            "file_path": "results/Multiple_CubeTarget_11/PlayerAgent.onnx",
            "reward": 6.36833330988884,
            "creation_time": 1725736886.711395,
            "auxillary_file_paths": [
                "results/Multiple_CubeTarget_11/PlayerAgent/PlayerAgent-112686.pt"
            ]
        }
    },
    "metadata": {
        "stats_format_version": "0.3.0",
        "mlagents_version": "0.30.0",
        "torch_version": "1.11.0"
    }
}